yardstiq_scaleway/plugin_loader.py
yardstiq_scaleway/scaleway_provider.py
yardstiq_scaleway/versions.py
yardstiq_scaleway-0.1.0.dist-info/licenses/LICENSE
yardstiq_scaleway-0.1.0.dist-info/METADATA
yardstiq_scaleway-0.1.0.dist-info/WHEEL
yardstiq_scaleway-0.1.0.dist-info/entry_points.txt
yardstiq_scaleway-0.1.0.dist-info/top_level.txt
yardstiq_scaleway-0.1.0.dist-info/RECORD
