Metadata-Version: 2.4
Name: yardstiq-scaleway
Version: 0.1.0
Summary: Scaleway provider implementation for Yardstiq
Project-URL: Repository, https://github.com/scaleway/yardstiq-scaleway
Requires-Python: >=3.12
License-File: LICENSE
Requires-Dist: yardstiq>=0.1.0
Requires-Dist: scaleway-qaas-client>=0.1.23
Requires-Dist: qami>=0.1.0
Dynamic: license-file
